filechunkcrud/__init__.py
filechunkcrud/file_handler.py
filechunkcrud-2025.5.180903.dist-info/licenses/LICENSE
tests/__init__.py
tests/test_file_handler.py
filechunkcrud-2025.5.180903.dist-info/METADATA
filechunkcrud-2025.5.180903.dist-info/WHEEL
filechunkcrud-2025.5.180903.dist-info/top_level.txt
filechunkcrud-2025.5.180903.dist-info/RECORD
