Metadata-Version: 2.4
Name: FileChunkCRUD
Version: 2025.5.180903
Summary: Python package for CRUD operations on large files in chunks.
Home-page: https://github.com/chigwell/FileChunkCRUD
Author: Eugene Evstafev
Author-email: chigwel@gmail.com
License-File: LICENSE
Dynamic: author
Dynamic: author-email
Dynamic: description
Dynamic: description-content-type
Dynamic: home-page
Dynamic: license-file
Dynamic: summary
